rest_framework_custom_paginations
tests
